{
  "updatedAt": "2026-06-27T19:51:54.308118+00:00",
  "sources": {
    "fofa": {
      "status": "empty",
      "items": [],
      "error": "No items parsed."
    },
    "urlhaus": {
      "status": "error",
      "items": [],
      "error": "HTTP Error 401: Unauthorized"
    },
    "reddit": {
      "status": "error",
      "items": [],
      "error": "HTTP Error 403: Blocked"
    },
    "trends24": {
      "status": "ok",
      "items": [
        {
          "title": "#WWENOC",
          "metric": "Trend",
          "url": "https://twitter.com/search?q=%23WWENOC",
          "platform": "X/Twitter"
        },
        {
          "title": "#UFCBaku",
          "metric": "Trend",
          "url": "https://twitter.com/search?q=%23UFCBaku",
          "platform": "X/Twitter"
        },
        {
          "title": "#NightOfChampions",
          "metric": "Trend",
          "url": "https://twitter.com/search?q=%23NightOfChampions",
          "platform": "X/Twitter"
        },
        {
          "title": "Gerrit Cole",
          "metric": "Trend",
          "url": "https://twitter.com/search?q=Gerrit%20Cole",
          "platform": "X/Twitter"
        },
        {
          "title": "Seth",
          "metric": "Trend",
          "url": "https://twitter.com/search?q=Seth",
          "platform": "X/Twitter"
        }
      ],
      "error": null
    },
    "googleTrends": {
      "status": "ok",
      "items": [
        {
          "title": "red sox",
          "traffic": "20000",
          "url": "https://trends.google.com/trending/rss?geo=US"
        },
        {
          "title": "brandon aiyuk",
          "traffic": "1000",
          "url": "https://trends.google.com/trending/rss?geo=US"
        },
        {
          "title": "herpes",
          "traffic": "500",
          "url": "https://trends.google.com/trending/rss?geo=US"
        },
        {
          "title": "soccer today",
          "traffic": "20000",
          "url": "https://trends.google.com/trending/rss?geo=US"
        },
        {
          "title": "rangers vs blue jays",
          "traffic": "20000",
          "url": "https://trends.google.com/trending/rss?geo=US"
        },
        {
          "title": "viktor hovland",
          "traffic": "500",
          "url": "https://trends.google.com/trending/rss?geo=US"
        },
        {
          "title": "ricky saints",
          "traffic": "1000",
          "url": "https://trends.google.com/trending/rss?geo=US"
        },
        {
          "title": "colombia portugal",
          "traffic": "1000",
          "url": "https://trends.google.com/trending/rss?geo=US"
        },
        {
          "title": "ausl",
          "traffic": "500",
          "url": "https://trends.google.com/trending/rss?geo=US"
        },
        {
          "title": "bron breakker",
          "traffic": "1000",
          "url": "https://trends.google.com/trending/rss?geo=US"
        }
      ],
      "error": null
    }
  }
}