{
  "updatedAt": "2026-05-20T19:23:27.594247+00:00",
  "sources": {
    "fofa": {
      "status": "empty",
      "items": [],
      "error": "No items parsed."
    },
    "urlhaus": {
      "status": "error",
      "items": [],
      "error": "HTTP Error 401: Unauthorized"
    },
    "reddit": {
      "status": "error",
      "items": [],
      "error": "HTTP Error 403: Blocked"
    },
    "trends24": {
      "status": "ok",
      "items": [
        {
          "title": "#PakistanForPeace",
          "metric": "Trend",
          "url": "https://twitter.com/search?q=%23PakistanForPeace",
          "platform": "X/Twitter"
        },
        {
          "title": "#NoSeremosColoniaSayona",
          "metric": "Trend",
          "url": "https://twitter.com/search?q=%23NoSeremosColoniaSayona",
          "platform": "X/Twitter"
        },
        {
          "title": "#BeyondTheGates",
          "metric": "Trend",
          "url": "https://twitter.com/search?q=%23BeyondTheGates",
          "platform": "X/Twitter"
        },
        {
          "title": "Ted Cruz",
          "metric": "Trend",
          "url": "https://twitter.com/search?q=Ted%20Cruz",
          "platform": "X/Twitter"
        },
        {
          "title": "Deanna",
          "metric": "Trend",
          "url": "https://twitter.com/search?q=Deanna",
          "platform": "X/Twitter"
        }
      ],
      "error": null
    },
    "googleTrends": {
      "status": "ok",
      "items": [
        {
          "title": "aaron rodgers",
          "traffic": "5000",
          "url": "https://trends.google.com/trending/rss?geo=US"
        },
        {
          "title": "mq-4c triton near cuba",
          "traffic": "200",
          "url": "https://trends.google.com/trending/rss?geo=US"
        },
        {
          "title": "bryson dechambeau",
          "traffic": "5000",
          "url": "https://trends.google.com/trending/rss?geo=US"
        },
        {
          "title": "freiburg fc",
          "traffic": "2000",
          "url": "https://trends.google.com/trending/rss?geo=US"
        },
        {
          "title": "david caruso",
          "traffic": "500",
          "url": "https://trends.google.com/trending/rss?geo=US"
        },
        {
          "title": "conference league final",
          "traffic": "500",
          "url": "https://trends.google.com/trending/rss?geo=US"
        },
        {
          "title": "minuteman iii",
          "traffic": "500",
          "url": "https://trends.google.com/trending/rss?geo=US"
        },
        {
          "title": "berserk",
          "traffic": "200",
          "url": "https://trends.google.com/trending/rss?geo=US"
        },
        {
          "title": "jack smith",
          "traffic": "1000",
          "url": "https://trends.google.com/trending/rss?geo=US"
        },
        {
          "title": "apple google ez lynk subpoena",
          "traffic": "500",
          "url": "https://trends.google.com/trending/rss?geo=US"
        }
      ],
      "error": null
    }
  }
}