{
  "updatedAt": "2026-07-07T18:31:05.183253+00:00",
  "sources": {
    "fofa": {
      "status": "empty",
      "items": [],
      "error": "No items parsed."
    },
    "urlhaus": {
      "status": "error",
      "items": [],
      "error": "HTTP Error 401: Unauthorized"
    },
    "reddit": {
      "status": "error",
      "items": [],
      "error": "HTTP Error 403: Blocked"
    },
    "trends24": {
      "status": "ok",
      "items": [
        {
          "title": "#bb28",
          "metric": "Trend",
          "url": "https://twitter.com/search?q=%23bb28",
          "platform": "X/Twitter"
        },
        {
          "title": "#ARGEGY",
          "metric": "Trend",
          "url": "https://twitter.com/search?q=%23ARGEGY",
          "platform": "X/Twitter"
        },
        {
          "title": "#gachiakuta171",
          "metric": "Trend",
          "url": "https://twitter.com/search?q=%23gachiakuta171",
          "platform": "X/Twitter"
        },
        {
          "title": "La Trice",
          "metric": "Trend",
          "url": "https://twitter.com/search?q=La%20Trice",
          "platform": "X/Twitter"
        },
        {
          "title": "Pfizer",
          "metric": "Trend",
          "url": "https://twitter.com/search?q=Pfizer",
          "platform": "X/Twitter"
        }
      ],
      "error": null
    },
    "googleTrends": {
      "status": "ok",
      "items": [
        {
          "title": "did argentina win",
          "traffic": "10000",
          "url": "https://trends.google.com/trending/rss?geo=US"
        },
        {
          "title": "a qué hora juega colombia",
          "traffic": "2000",
          "url": "https://trends.google.com/trending/rss?geo=US"
        },
        {
          "title": "golden boot race 2026",
          "traffic": "1000",
          "url": "https://trends.google.com/trending/rss?geo=US"
        },
        {
          "title": "soccer",
          "traffic": "100000",
          "url": "https://trends.google.com/trending/rss?geo=US"
        },
        {
          "title": "argentina jersey",
          "traffic": "500",
          "url": "https://trends.google.com/trending/rss?geo=US"
        },
        {
          "title": "geno auriemma",
          "traffic": "500",
          "url": "https://trends.google.com/trending/rss?geo=US"
        },
        {
          "title": "how old is messi",
          "traffic": "200",
          "url": "https://trends.google.com/trending/rss?geo=US"
        },
        {
          "title": "fifa rankings",
          "traffic": "10000",
          "url": "https://trends.google.com/trending/rss?geo=US"
        },
        {
          "title": "world cu",
          "traffic": "500",
          "url": "https://trends.google.com/trending/rss?geo=US"
        },
        {
          "title": "argentina next game",
          "traffic": "2000",
          "url": "https://trends.google.com/trending/rss?geo=US"
        }
      ],
      "error": null
    }
  }
}