{
  "updatedAt": "2026-07-18T11:01:22.013872+00:00",
  "sources": {
    "fofa": {
      "status": "empty",
      "items": [],
      "error": "No items parsed."
    },
    "urlhaus": {
      "status": "error",
      "items": [],
      "error": "HTTP Error 401: Unauthorized"
    },
    "reddit": {
      "status": "error",
      "items": [],
      "error": "HTTP Error 403: Blocked"
    },
    "trends24": {
      "status": "ok",
      "items": [
        {
          "title": "#PerthSantaConcertD1",
          "metric": "Trend",
          "url": "https://twitter.com/search?q=%23PerthSantaConcertD1",
          "platform": "X/Twitter"
        },
        {
          "title": "#NewShapeofGalaxy",
          "metric": "Trend",
          "url": "https://twitter.com/search?q=%23NewShapeofGalaxy",
          "platform": "X/Twitter"
        },
        {
          "title": "#STARDOM",
          "metric": "Trend",
          "url": "https://twitter.com/search?q=%23STARDOM",
          "platform": "X/Twitter"
        },
        {
          "title": "Jimothy",
          "metric": "Trend",
          "url": "https://twitter.com/search?q=Jimothy",
          "platform": "X/Twitter"
        },
        {
          "title": "Odysseus",
          "metric": "Trend",
          "url": "https://twitter.com/search?q=Odysseus",
          "platform": "X/Twitter"
        }
      ],
      "error": null
    },
    "googleTrends": {
      "status": "ok",
      "items": [
        {
          "title": "local weather",
          "traffic": "100",
          "url": "https://trends.google.com/trending/rss?geo=US"
        },
        {
          "title": "epileptic",
          "traffic": "100",
          "url": "https://trends.google.com/trending/rss?geo=US"
        },
        {
          "title": "senna",
          "traffic": "100",
          "url": "https://trends.google.com/trending/rss?geo=US"
        },
        {
          "title": "sweeteners",
          "traffic": "100",
          "url": "https://trends.google.com/trending/rss?geo=US"
        },
        {
          "title": "michael weatherly",
          "traffic": "200",
          "url": "https://trends.google.com/trending/rss?geo=US"
        },
        {
          "title": "jason statham",
          "traffic": "200",
          "url": "https://trends.google.com/trending/rss?geo=US"
        },
        {
          "title": "air quality index columbus ohio",
          "traffic": "1000",
          "url": "https://trends.google.com/trending/rss?geo=US"
        },
        {
          "title": "central ohio air quality alerts",
          "traffic": "100",
          "url": "https://trends.google.com/trending/rss?geo=US"
        },
        {
          "title": "fantasy",
          "traffic": "100",
          "url": "https://trends.google.com/trending/rss?geo=US"
        },
        {
          "title": "sunny hostin",
          "traffic": "100",
          "url": "https://trends.google.com/trending/rss?geo=US"
        }
      ],
      "error": null
    }
  }
}