{
  "updatedAt": "2026-06-23T12:31:17.627427+00:00",
  "sources": {
    "fofa": {
      "status": "empty",
      "items": [],
      "error": "No items parsed."
    },
    "urlhaus": {
      "status": "error",
      "items": [],
      "error": "HTTP Error 401: Unauthorized"
    },
    "reddit": {
      "status": "error",
      "items": [],
      "error": "HTTP Error 403: Blocked"
    },
    "trends24": {
      "status": "ok",
      "items": [
        {
          "title": "#QG694",
          "metric": "Trend",
          "url": "https://twitter.com/search?q=%23QG694",
          "platform": "X/Twitter"
        },
        {
          "title": "#ZatimaOnParamountPlus",
          "metric": "Trend",
          "url": "https://twitter.com/search?q=%23ZatimaOnParamountPlus",
          "platform": "X/Twitter"
        },
        {
          "title": "#TESTME_9",
          "metric": "Trend",
          "url": "https://twitter.com/search?q=%23TESTME_9",
          "platform": "X/Twitter"
        },
        {
          "title": "Happy 35th",
          "metric": "Trend",
          "url": "https://twitter.com/search?q=Happy%2035th",
          "platform": "X/Twitter"
        },
        {
          "title": "Cell",
          "metric": "Trend",
          "url": "https://twitter.com/search?q=Cell",
          "platform": "X/Twitter"
        }
      ],
      "error": null
    },
    "googleTrends": {
      "status": "ok",
      "items": [
        {
          "title": "bees",
          "traffic": "1000",
          "url": "https://trends.google.com/trending/rss?geo=US"
        },
        {
          "title": "irán",
          "traffic": "500",
          "url": "https://trends.google.com/trending/rss?geo=US"
        },
        {
          "title": "dan goldman",
          "traffic": "2000",
          "url": "https://trends.google.com/trending/rss?geo=US"
        },
        {
          "title": "amazon prime",
          "traffic": "20000",
          "url": "https://trends.google.com/trending/rss?geo=US"
        },
        {
          "title": "garrett crochet",
          "traffic": "200",
          "url": "https://trends.google.com/trending/rss?geo=US"
        },
        {
          "title": "jaden mcdaniels",
          "traffic": "200",
          "url": "https://trends.google.com/trending/rss?geo=US"
        },
        {
          "title": "xrp",
          "traffic": "500",
          "url": "https://trends.google.com/trending/rss?geo=US"
        },
        {
          "title": "luke bryan jason aldean lawsuit",
          "traffic": "500",
          "url": "https://trends.google.com/trending/rss?geo=US"
        },
        {
          "title": "rocket launch today",
          "traffic": "2000",
          "url": "https://trends.google.com/trending/rss?geo=US"
        },
        {
          "title": "shipping",
          "traffic": "500",
          "url": "https://trends.google.com/trending/rss?geo=US"
        }
      ],
      "error": null
    }
  }
}