{
  "updatedAt": "2026-07-12T20:42:46.411810+00:00",
  "sources": {
    "fofa": {
      "status": "empty",
      "items": [],
      "error": "No items parsed."
    },
    "urlhaus": {
      "status": "error",
      "items": [],
      "error": "HTTP Error 401: Unauthorized"
    },
    "reddit": {
      "status": "error",
      "items": [],
      "error": "HTTP Error 403: Blocked"
    },
    "trends24": {
      "status": "ok",
      "items": [
        {
          "title": "#Wimbledon",
          "metric": "Trend",
          "url": "https://twitter.com/search?q=%23Wimbledon",
          "platform": "X/Twitter"
        },
        {
          "title": "#SeductiveSunday",
          "metric": "Trend",
          "url": "https://twitter.com/search?q=%23SeductiveSunday",
          "platform": "X/Twitter"
        },
        {
          "title": "#Olandria",
          "metric": "Trend",
          "url": "https://twitter.com/search?q=%23Olandria",
          "platform": "X/Twitter"
        },
        {
          "title": "Congratulations Ben",
          "metric": "Trend",
          "url": "https://twitter.com/search?q=Congratulations%20Ben",
          "platform": "X/Twitter"
        },
        {
          "title": "Tapper",
          "metric": "Trend",
          "url": "https://twitter.com/search?q=Tapper",
          "platform": "X/Twitter"
        }
      ],
      "error": null
    },
    "googleTrends": {
      "status": "ok",
      "items": [
        {
          "title": "austin reaves",
          "traffic": "500",
          "url": "https://trends.google.com/trending/rss?geo=US"
        },
        {
          "title": "nwsl",
          "traffic": "2000",
          "url": "https://trends.google.com/trending/rss?geo=US"
        },
        {
          "title": "alianza lima vs deportivo cali",
          "traffic": "500",
          "url": "https://trends.google.com/trending/rss?geo=US"
        },
        {
          "title": "weather houston",
          "traffic": "200",
          "url": "https://trends.google.com/trending/rss?geo=US"
        },
        {
          "title": "mets",
          "traffic": "10000",
          "url": "https://trends.google.com/trending/rss?geo=US"
        },
        {
          "title": "red sox",
          "traffic": "5000",
          "url": "https://trends.google.com/trending/rss?geo=US"
        },
        {
          "title": "iran attacks uae today",
          "traffic": "5000",
          "url": "https://trends.google.com/trending/rss?geo=US"
        },
        {
          "title": "patrick peterson",
          "traffic": "5000",
          "url": "https://trends.google.com/trending/rss?geo=US"
        },
        {
          "title": "dbacks - dodgers",
          "traffic": "2000",
          "url": "https://trends.google.com/trending/rss?geo=US"
        },
        {
          "title": "mackenzie scott",
          "traffic": "200",
          "url": "https://trends.google.com/trending/rss?geo=US"
        }
      ],
      "error": null
    }
  }
}