{
  "updatedAt": "2026-06-28T08:26:23.807762+00:00",
  "sources": {
    "fofa": {
      "status": "empty",
      "items": [],
      "error": "No items parsed."
    },
    "urlhaus": {
      "status": "error",
      "items": [],
      "error": "HTTP Error 401: Unauthorized"
    },
    "reddit": {
      "status": "error",
      "items": [],
      "error": "HTTP Error 403: Blocked"
    },
    "trends24": {
      "status": "ok",
      "items": [
        {
          "title": "#PPxSTAKE",
          "metric": "Trend",
          "url": "https://twitter.com/search?q=%23PPxSTAKE",
          "platform": "X/Twitter"
        },
        {
          "title": "#boxing",
          "metric": "Trend",
          "url": "https://twitter.com/search?q=%23boxing",
          "platform": "X/Twitter"
        },
        {
          "title": "#GCWWanted",
          "metric": "Trend",
          "url": "https://twitter.com/search?q=%23GCWWanted",
          "platform": "X/Twitter"
        },
        {
          "title": "#Toonami",
          "metric": "Trend",
          "url": "https://twitter.com/search?q=%23Toonami",
          "platform": "X/Twitter"
        },
        {
          "title": "Gamboa",
          "metric": "Trend",
          "url": "https://twitter.com/search?q=Gamboa",
          "platform": "X/Twitter"
        }
      ],
      "error": null
    },
    "googleTrends": {
      "status": "ok",
      "items": [
        {
          "title": "selena gomez",
          "traffic": "100",
          "url": "https://trends.google.com/trending/rss?geo=US"
        },
        {
          "title": "zim vs ban",
          "traffic": "500",
          "url": "https://trends.google.com/trending/rss?geo=US"
        },
        {
          "title": "buc ee's locations",
          "traffic": "500",
          "url": "https://trends.google.com/trending/rss?geo=US"
        },
        {
          "title": "from season 5",
          "traffic": "2000",
          "url": "https://trends.google.com/trending/rss?geo=US"
        },
        {
          "title": "msi lol",
          "traffic": "500",
          "url": "https://trends.google.com/trending/rss?geo=US"
        },
        {
          "title": "weather tornado warning",
          "traffic": "2000",
          "url": "https://trends.google.com/trending/rss?geo=US"
        },
        {
          "title": "cardi b",
          "traffic": "1000",
          "url": "https://trends.google.com/trending/rss?geo=US"
        },
        {
          "title": "posiciones de selección de fútbol de argelia contra selección de fútbol de austria",
          "traffic": "20000",
          "url": "https://trends.google.com/trending/rss?geo=US"
        },
        {
          "title": "vergil ortiz",
          "traffic": "2000",
          "url": "https://trends.google.com/trending/rss?geo=US"
        },
        {
          "title": "amanda bynes",
          "traffic": "1000",
          "url": "https://trends.google.com/trending/rss?geo=US"
        }
      ],
      "error": null
    }
  }
}