{
  "updatedAt": "2026-05-20T13:37:46.746342+00:00",
  "sources": {
    "fofa": {
      "status": "empty",
      "items": [],
      "error": "No items parsed."
    },
    "urlhaus": {
      "status": "error",
      "items": [],
      "error": "HTTP Error 401: Unauthorized"
    },
    "reddit": {
      "status": "error",
      "items": [],
      "error": "HTTP Error 403: Blocked"
    },
    "trends24": {
      "status": "ok",
      "items": [
        {
          "title": "#TheBoys",
          "metric": "Trend",
          "url": "https://twitter.com/search?q=%23TheBoys",
          "platform": "X/Twitter"
        },
        {
          "title": "#LOLFanFest2026LIVE",
          "metric": "Trend",
          "url": "https://twitter.com/search?q=%23LOLFanFest2026LIVE",
          "platform": "X/Twitter"
        },
        {
          "title": "#WednesdayWisdom",
          "metric": "Trend",
          "url": "https://twitter.com/search?q=%23WednesdayWisdom",
          "platform": "X/Twitter"
        },
        {
          "title": "Congrats Scott",
          "metric": "Trend",
          "url": "https://twitter.com/search?q=Congrats%20Scott",
          "platform": "X/Twitter"
        },
        {
          "title": "#WednesdayMotivation",
          "metric": "Trend",
          "url": "https://twitter.com/search?q=%23WednesdayMotivation",
          "platform": "X/Twitter"
        }
      ],
      "error": null
    },
    "googleTrends": {
      "status": "ok",
      "items": [
        {
          "title": "james murdoch",
          "traffic": "200",
          "url": "https://trends.google.com/trending/rss?geo=US"
        },
        {
          "title": "kkr vs mi",
          "traffic": "500",
          "url": "https://trends.google.com/trending/rss?geo=US"
        },
        {
          "title": "florida georgia line",
          "traffic": "200",
          "url": "https://trends.google.com/trending/rss?geo=US"
        },
        {
          "title": "golden dome",
          "traffic": "500",
          "url": "https://trends.google.com/trending/rss?geo=US"
        },
        {
          "title": "intuit layoffs",
          "traffic": "200",
          "url": "https://trends.google.com/trending/rss?geo=US"
        },
        {
          "title": "disney plus",
          "traffic": "2000",
          "url": "https://trends.google.com/trending/rss?geo=US"
        },
        {
          "title": "colin jost",
          "traffic": "1000",
          "url": "https://trends.google.com/trending/rss?geo=US"
        },
        {
          "title": "intuit",
          "traffic": "500",
          "url": "https://trends.google.com/trending/rss?geo=US"
        },
        {
          "title": "deportation",
          "traffic": "500",
          "url": "https://trends.google.com/trending/rss?geo=US"
        },
        {
          "title": "merritt island",
          "traffic": "200",
          "url": "https://trends.google.com/trending/rss?geo=US"
        }
      ],
      "error": null
    }
  }
}