{
  "updatedAt": "2026-07-23T11:50:15.531469+00:00",
  "sources": {
    "fofa": {
      "status": "empty",
      "items": [],
      "error": "No items parsed."
    },
    "urlhaus": {
      "status": "error",
      "items": [],
      "error": "HTTP Error 401: Unauthorized"
    },
    "reddit": {
      "status": "error",
      "items": [],
      "error": "HTTP Error 403: Blocked"
    },
    "trends24": {
      "status": "ok",
      "items": [
        {
          "title": "#holodori",
          "metric": "Trend",
          "url": "https://twitter.com/search?q=%23holodori",
          "platform": "X/Twitter"
        },
        {
          "title": "#AEWDynamite",
          "metric": "Trend",
          "url": "https://twitter.com/search?q=%23AEWDynamite",
          "platform": "X/Twitter"
        },
        {
          "title": "#LingOrmAtDiorSiamParagon",
          "metric": "Trend",
          "url": "https://twitter.com/search?q=%23LingOrmAtDiorSiamParagon",
          "platform": "X/Twitter"
        },
        {
          "title": "Clayface",
          "metric": "Trend",
          "url": "https://twitter.com/search?q=Clayface",
          "platform": "X/Twitter"
        },
        {
          "title": "Pinky Herman",
          "metric": "Trend",
          "url": "https://twitter.com/search?q=Pinky%20Herman",
          "platform": "X/Twitter"
        }
      ],
      "error": null
    },
    "googleTrends": {
      "status": "ok",
      "items": [
        {
          "title": "taco bell specials",
          "traffic": "200",
          "url": "https://trends.google.com/trending/rss?geo=US"
        },
        {
          "title": "nyt connections hints",
          "traffic": "200",
          "url": "https://trends.google.com/trending/rss?geo=US"
        },
        {
          "title": "jayden wareham",
          "traffic": "200",
          "url": "https://trends.google.com/trending/rss?geo=US"
        },
        {
          "title": "2026 super el nino forecast",
          "traffic": "500",
          "url": "https://trends.google.com/trending/rss?geo=US"
        },
        {
          "title": "wral",
          "traffic": "200",
          "url": "https://trends.google.com/trending/rss?geo=US"
        },
        {
          "title": "sebastian baez",
          "traffic": "200",
          "url": "https://trends.google.com/trending/rss?geo=US"
        },
        {
          "title": "3m open",
          "traffic": "200",
          "url": "https://trends.google.com/trending/rss?geo=US"
        },
        {
          "title": "earthquake oklahoma",
          "traffic": "200",
          "url": "https://trends.google.com/trending/rss?geo=US"
        },
        {
          "title": "mayank yadav",
          "traffic": "500",
          "url": "https://trends.google.com/trending/rss?geo=US"
        },
        {
          "title": "prince george birthday",
          "traffic": "200",
          "url": "https://trends.google.com/trending/rss?geo=US"
        }
      ],
      "error": null
    }
  }
}